{
  "code": 200,
  "msg": "操作成功",
  "data": [
    {
      "map": {
        "erpTaskHours": "17.60",
        "erpTaskName": "安徽滁州技师学院特种作业培训考试实训基地"
      }
    },
    {
      "map": {
        "erpTaskHours": "13.63",
        "erpTaskName": "淮北工业学校考点修改"
      }
    },
    {
      "map": {
        "erpTaskHours": "10.12",
        "erpTaskName": "江苏矿山安全培训实操基地建设"
      }
    },
    {
      "map": {
        "erpTaskHours": "5.67",
        "erpTaskName": "江苏矿山安全培训实操基地"
      }
    },
    {
      "map": {
        "erpTaskHours": "5.45",
        "erpTaskName": "贵州首钢水钢技师学院安全技术培训中心"
      }
    },
    {
      "map": {
        "erpTaskHours": "4.46",
        "erpTaskName": "六盘水广丰职业培训学校"
      }
    },
    {
      "map": {
        "erpTaskHours": "4.45",
        "erpTaskName": "海南矿业培训中心"
      }
    },
    {
      "map": {
        "erpTaskHours": "4.31",
        "erpTaskName": "抚顺石化实训基地项目"
      }
    },
    {
      "map": {
        "erpTaskHours": "3.20",
        "erpTaskName": "七台河江河化工园区"
      }
    },
    {
      "map": {
        "erpTaskHours": "2.96",
        "erpTaskName": "遂川县考点（老图修改）"
      }
    },
    {
      "map": {
        "erpTaskHours": "2.61",
        "erpTaskName": "榆林中安中诚"
      }
    },
    {
      "map": {
        "erpTaskHours": "2.61",
        "erpTaskName": "云南全政安全技能培训有限公司"
      }
    },
    {
      "map": {
        "erpTaskHours": "2.41",
        "erpTaskName": "重庆工业职业学院危化特种作业考点设备建设"
      }
    },
    {
      "map": {
        "erpTaskHours": "2.40",
        "erpTaskName": "怀化市应急管理局考试中心"
      }
    },
    {
      "map": {
        "erpTaskHours": "2.13",
        "erpTaskName": "云南全政安全技能培训有限公司（老图修改）"
      }
    },
    {
      "map": {
        "erpTaskHours": "2.04",
        "erpTaskName": "绍兴开放大学"
      }
    },
    {
      "map": {
        "erpTaskHours": "1.88",
        "erpTaskName": "陕西榆林实训楼项目"
      }
    },
    {
      "map": {
        "erpTaskHours": "1.30",
        "erpTaskName": "长沙建筑学校"
      }
    },
    {
      "map": {
        "erpTaskHours": "1.26",
        "erpTaskName": "抚顺石化实训基地项目"
      }
    },
    {
      "map": {
        "erpTaskHours": "0.63",
        "erpTaskName": "贵州首钢水钢技师学院安全技术培训中心"
      }
    },
    {
      "map": {
        "erpTaskHours": "0.61",
        "erpTaskName": "抚顺石化实训基地项目（老图修改）"
      }
    },
    {
      "map": {
        "erpTaskHours": "0.60",
        "erpTaskName": "九泰安全培训修改"
      }
    },
    {
      "map": {
        "erpTaskHours": "0.41",
        "erpTaskName": "威宁彝族回族苗族自治县安全生产协会安全技术培训中心（老图修改）"
      }
    },
    {
      "map": {
        "erpTaskHours": "0.15",
        "erpTaskName": "太仓安宣（焊接作业）"
      }
    }
  ],
  "rows": null
}
